[
    {
        "id": "37722",
        "event_id": "13886",
        "title": "Market Holiday - All Saints' Day (AT, HR, HU, LT, LU, PL, SK)",
        "currency": "EUR",
        "country_code": "EU",
        "start_date": "2011-11-01 00:00:00",
        "start_date_u": "1320105600",
        "end_date": "2011-11-01 23:59:00",
        "sessions": [
            "sydney",
            "tokyo"
        ],
        "impact": "2",
        "previous": null,
        "forecast": null,
        "actual": null,
        "actual_verdict": null,
        "revised": false,
        "unit": "",
        "binary": "1100",
        "slug": "market-holiday-all-saints-day-at",
        "remembered": false
    },
    {
        "id": "39020",
        "event_id": "143",
        "title": "ANZ Commodity Price",
        "currency": "NZD",
        "country_code": "NZ",
        "start_date": "2011-11-01 00:00:00",
        "start_date_u": "1320105600",
        "end_date": "2011-11-01 23:59:00",
        "sessions": [
            "sydney",
            "tokyo"
        ],
        "impact": "1",
        "previous": -1.3,
        "forecast": null,
        "actual": -3.5,
        "actual_verdict": null,
        "revised": true,
        "unit": "% m/m",
        "binary": "1100",
        "slug": "anz-commodity-price",
        "remembered": false
    },
    {
        "id": "37939",
        "event_id": "783",
        "title": "House Price Index",
        "currency": "AUD",
        "country_code": "AU",
        "start_date": "2011-11-01 00:30:00",
        "start_date_u": "1320107400",
        "end_date": "2011-11-01 23:59:00",
        "sessions": [
            "sydney",
            "tokyo"
        ],
        "impact": "1",
        "previous": -0.5,
        "forecast": -1.5,
        "actual": -1.9,
        "actual_verdict": "worse",
        "revised": true,
        "unit": "% q/q",
        "binary": "1100",
        "slug": "house-price-index-aud-au",
        "remembered": false
    },
    {
        "id": "39021",
        "event_id": "12884",
        "title": "Chinese PMI Manufacturing",
        "currency": "CNY",
        "country_code": "CN",
        "start_date": "2011-11-01 01:00:00",
        "start_date_u": "1320109200",
        "end_date": "2011-11-01 23:59:00",
        "sessions": [
            "sydney",
            "tokyo"
        ],
        "impact": "3",
        "previous": 51.2,
        "forecast": 51.8,
        "actual": 50.4,
        "actual_verdict": "worse",
        "revised": true,
        "unit": "index",
        "binary": "1100",
        "slug": "pmi-manufacturing-cny-cn-746",
        "remembered": false
    },
    {
        "id": "33908",
        "event_id": "13347",
        "title": "RBA - Overnight Rate",
        "currency": "AUD",
        "country_code": "AU",
        "start_date": "2011-11-01 03:30:00",
        "start_date_u": "1320118200",
        "end_date": "2011-11-01 23:59:00",
        "sessions": [
            "sydney",
            "tokyo"
        ],
        "impact": "3",
        "previous": 4.75,
        "forecast": 4.5,
        "actual": 4.5,
        "actual_verdict": "neutral",
        "revised": true,
        "unit": "%",
        "binary": "1100",
        "slug": "rba-overnight-rate",
        "remembered": false
    },
    {
        "id": "39048",
        "event_id": "12525",
        "title": "Vehicle Sales",
        "currency": "JPY",
        "country_code": "JP",
        "start_date": "2011-11-01 05:00:00",
        "start_date_u": "1320123600",
        "end_date": "2011-11-01 23:59:59",
        "sessions": [
            "sydney",
            "tokyo"
        ],
        "impact": "1",
        "previous": 1.7,
        "forecast": null,
        "actual": 28.3,
        "actual_verdict": null,
        "revised": true,
        "unit": "% y/y",
        "binary": "1100",
        "slug": "vehicle-sales-jpy-jp",
        "remembered": false
    },
    {
        "id": "38716",
        "event_id": "163",
        "title": "Nationwide house prices (sa)",
        "currency": "GBP",
        "country_code": "GB",
        "start_date": "2011-11-01 07:00:00",
        "start_date_u": "1320130800",
        "end_date": "2011-11-01 23:59:00",
        "sessions": [
            "tokyo",
            "london"
        ],
        "impact": "2",
        "previous": 0.1,
        "forecast": null,
        "actual": 0.4,
        "actual_verdict": null,
        "revised": true,
        "unit": "% m/m",
        "binary": "0110",
        "slug": "nationwide-house-prices-sa",
        "remembered": false
    },
    {
        "id": "38717",
        "event_id": "164",
        "title": "Nationwide house prices (nsa)",
        "currency": "GBP",
        "country_code": "GB",
        "start_date": "2011-11-01 07:00:00",
        "start_date_u": "1320130800",
        "end_date": "2011-11-01 23:59:00",
        "sessions": [
            "tokyo",
            "london"
        ],
        "impact": "2",
        "previous": -0.3,
        "forecast": 0.5,
        "actual": 0.8,
        "actual_verdict": "better",
        "revised": true,
        "unit": "% y/y",
        "binary": "0110",
        "slug": "nationwide-house-prices-nsa",
        "remembered": false
    },
    {
        "id": "39018",
        "event_id": "106",
        "title": "Retail Sales",
        "currency": "CHF",
        "country_code": "CH",
        "start_date": "2011-11-01 08:15:00",
        "start_date_u": "1320135300",
        "end_date": "2011-11-01 23:59:59",
        "sessions": [
            "london"
        ],
        "impact": "2",
        "previous": -0.8,
        "forecast": null,
        "actual": -1.4,
        "actual_verdict": null,
        "revised": true,
        "unit": "% y/y",
        "binary": "0010",
        "slug": "retail-sales",
        "remembered": false
    },
    {
        "id": "39019",
        "event_id": "10648",
        "title": "Manufacturing PMI",
        "currency": "CHF",
        "country_code": "CH",
        "start_date": "2011-11-01 08:30:00",
        "start_date_u": "1320136200",
        "end_date": "2011-11-01 23:59:00",
        "sessions": [
            "london"
        ],
        "impact": "2",
        "previous": 48.2,
        "forecast": 47.7,
        "actual": 46.5,
        "actual_verdict": "worse",
        "revised": true,
        "unit": "index",
        "binary": "0010",
        "slug": "manufacturing-pmi-chf-ch",
        "remembered": false
    },
    {
        "id": "39059",
        "event_id": "10647",
        "title": "CIPS Manufacturing PMI",
        "currency": "GBP",
        "country_code": "GB",
        "start_date": "2011-11-01 09:28:00",
        "start_date_u": "1320139680",
        "end_date": "2011-11-01 23:59:00",
        "sessions": [
            "london"
        ],
        "impact": "3",
        "previous": 50.8,
        "forecast": 50,
        "actual": 47.8,
        "actual_verdict": "worse",
        "revised": true,
        "unit": "index",
        "binary": "0010",
        "slug": "cips-manufacturing-pmi",
        "remembered": false
    },
    {
        "id": "38496",
        "event_id": "3267",
        "title": "GDP (1st Est.)",
        "currency": "GBP",
        "country_code": "GB",
        "start_date": "2011-11-01 09:30:00",
        "start_date_u": "1320139800",
        "end_date": "2011-11-01 23:59:00",
        "sessions": [
            "london"
        ],
        "impact": "3",
        "previous": 0.6,
        "forecast": 0.4,
        "actual": 0.5,
        "actual_verdict": "better",
        "revised": true,
        "unit": "% y/y",
        "binary": "0010",
        "slug": "gdp-1st-est-gbp-gb-890",
        "remembered": false
    },
    {
        "id": "38497",
        "event_id": "3268",
        "title": "GDP (1st Est.)",
        "currency": "GBP",
        "country_code": "GB",
        "start_date": "2011-11-01 09:30:00",
        "start_date_u": "1320139800",
        "end_date": "2011-11-01 23:59:00",
        "sessions": [
            "london"
        ],
        "impact": "3",
        "previous": 0.1,
        "forecast": 0.3,
        "actual": 0.5,
        "actual_verdict": "better",
        "revised": true,
        "unit": "% q/q",
        "binary": "0010",
        "slug": "gdp-1st-est-gbp-gb-971",
        "remembered": false
    },
    {
        "id": "39107",
        "event_id": "11668",
        "title": "Index of Services",
        "currency": "GBP",
        "country_code": "GB",
        "start_date": "2011-11-01 09:30:00",
        "start_date_u": "1320139800",
        "end_date": "2011-11-01 23:59:00",
        "sessions": [
            "london"
        ],
        "impact": "1",
        "previous": -0.2,
        "forecast": null,
        "actual": 0.4,
        "actual_verdict": null,
        "revised": true,
        "unit": "% m/m",
        "binary": "0010",
        "slug": "index-of-services",
        "remembered": false
    },
    {
        "id": "39108",
        "event_id": "11669",
        "title": "Index of Services",
        "currency": "GBP",
        "country_code": "GB",
        "start_date": "2011-11-01 09:30:00",
        "start_date_u": "1320139800",
        "end_date": "2011-11-01 23:59:00",
        "sessions": [
            "london"
        ],
        "impact": "1",
        "previous": 0.8,
        "forecast": 0.5,
        "actual": 0.6,
        "actual_verdict": "better",
        "revised": true,
        "unit": "% q/q",
        "binary": "0010",
        "slug": "index-of-services-gbp-gb",
        "remembered": false
    },
    {
        "id": "39564",
        "event_id": "13980",
        "title": "World Bank President Zoellick speaks on the G20 Meeting, Food Price Volatility and other risks to the global economy",
        "currency": "",
        "country_code": "WLD",
        "start_date": "2011-11-01 13:30:00",
        "start_date_u": "1320154200",
        "end_date": "2011-11-01 23:59:00",
        "sessions": [
            "london",
            "nyc"
        ],
        "impact": "1",
        "previous": null,
        "forecast": null,
        "actual": null,
        "actual_verdict": null,
        "revised": false,
        "unit": "",
        "binary": "0011",
        "slug": "world-bank-president-zoellick-sp",
        "remembered": false
    },
    {
        "id": "39046",
        "event_id": "127",
        "title": "ISM Manufacturing",
        "currency": "USD",
        "country_code": "US",
        "start_date": "2011-11-01 14:00:00",
        "start_date_u": "1320156000",
        "end_date": "2011-11-01 23:59:00",
        "sessions": [
            "london",
            "nyc"
        ],
        "impact": "3",
        "previous": 51.6,
        "forecast": 52,
        "actual": 50.8,
        "actual_verdict": "worse",
        "revised": true,
        "unit": "index",
        "binary": "0011",
        "slug": "ism-manufacturing",
        "remembered": false
    },
    {
        "id": "39047",
        "event_id": "128",
        "title": "Construction Spending",
        "currency": "USD",
        "country_code": "US",
        "start_date": "2011-11-01 14:00:00",
        "start_date_u": "1320156000",
        "end_date": "2011-11-01 23:59:00",
        "sessions": [
            "london",
            "nyc"
        ],
        "impact": "1",
        "previous": 1.6,
        "forecast": 0.3,
        "actual": 0.2,
        "actual_verdict": "worse",
        "revised": true,
        "unit": "% m/m",
        "binary": "0011",
        "slug": "construction-spending",
        "remembered": false
    },
    {
        "id": "34349",
        "event_id": "11643",
        "title": "Federal Reserve Bank of Minneapolis President Kocherlakota speaks to the Wisconsin Banker's Association",
        "currency": "USD",
        "country_code": "US",
        "start_date": "2011-11-01 19:00:00",
        "start_date_u": "1320174000",
        "end_date": "2011-11-01 23:59:00",
        "sessions": [
            "nyc"
        ],
        "impact": "1",
        "previous": null,
        "forecast": null,
        "actual": null,
        "actual_verdict": null,
        "revised": false,
        "unit": "",
        "binary": "0001",
        "slug": "federal-reserve-bank-of-minneapo-usd-us-929",
        "remembered": false
    },
    {
        "id": "39064",
        "event_id": "125",
        "title": "Vehicle Sales",
        "currency": "USD",
        "country_code": "US",
        "start_date": "2011-11-01 21:00:00",
        "start_date_u": "1320181200",
        "end_date": "2011-11-01 23:59:00",
        "sessions": [
            "sydney",
            "nyc"
        ],
        "impact": "1",
        "previous": 13.04,
        "forecast": 13.2,
        "actual": 13.2,
        "actual_verdict": "neutral",
        "revised": true,
        "unit": "mn",
        "binary": "1001",
        "slug": "vehicle-sales",
        "remembered": false
    }
]
